telescoop_backup/__init__.py
telescoop_backup/apps.py
telescoop_backup/backup.py
telescoop_backup/managers.py
telescoop_backup/media_backup.py
telescoop_backup/security_backup.py
telescoop_backup/serializers.py
telescoop_backup/tests.py
telescoop_backup/urls.py
telescoop_backup/views.py
telescoop_backup/management/__init__.py
telescoop_backup/management/commands/__init__.py
telescoop_backup/management/commands/backup_db.py
telescoop_backup/migrations/__init__.py
telescoop_backup-0.6.2.dist-info/licenses/LICENSE
telescoop_backup-0.6.2.dist-info/METADATA
telescoop_backup-0.6.2.dist-info/WHEEL
telescoop_backup-0.6.2.dist-info/top_level.txt
telescoop_backup-0.6.2.dist-info/RECORD
