Metadata-Version: 2.4
Name: telescoop-backup
Version: 0.6.2
Summary: Django app to backup Sqlite or Postgres database to an S3 Object Storage.
Home-page: https://gitlab.com/telescoop-public/django-apps/telescoop-backup
Author: TelesCoop SARL SCOP
Author-email: contact@telescoop.fr
License: BSD-3-Clause
Classifier: Environment :: Web Environment
Classifier: Framework :: Django
Classifier: Intended Audience :: Developers
Classifier: License :: OSI Approved :: BSD License
Classifier: Operating System :: OS Independent
Classifier: Programming Language :: Python
Classifier: Programming Language :: Python :: 3
Classifier: Programming Language :: Python :: 3 :: Only
Classifier: Programming Language :: Python :: 3.6
Classifier: Programming Language :: Python :: 3.7
Classifier: Programming Language :: Python :: 3.8
Classifier: Programming Language :: Python :: 3.9
Classifier: Programming Language :: Python :: 3.10
Classifier: Programming Language :: Python :: 3.11
Classifier: Programming Language :: Python :: 3.12
Classifier: Topic :: Internet :: WWW/HTTP
Classifier: Topic :: Internet :: WWW/HTTP :: Dynamic Content
License-File: LICENSE
Requires-Dist: boto3<2,>=1.34.0
Requires-Dist: tqdm>=4.0.0
Requires-Dist: humanize>=4.0.0
Dynamic: license-file
